CHANGES.txt
MANIFEST.in
README.txt
setup.py
src/rsl/__init__.py
src/rsl.soap11.egg-info/PKG-INFO
src/rsl.soap11.egg-info/SOURCES.txt
src/rsl.soap11.egg-info/dependency_links.txt
src/rsl.soap11.egg-info/entry_points.txt
src/rsl.soap11.egg-info/namespace_packages.txt
src/rsl.soap11.egg-info/requires.txt
src/rsl.soap11.egg-info/top_level.txt
src/rsl/soap11/__init__.py
src/rsl/soap11/factories.py
src/rsl/soap11/fault.py
src/rsl/soap11/namespace.py
src/rsl/soap11/proxy.py
src/rsl/soap11/serializer.py
src/rsl/soap11/soapenc.py
src/rsl/soap11/wsdl1.py
src/rsl/soap11/xsds/soapenc.xsd
src/rsl/soap11/xsds/soapenv.xsd
src/rsl/soap11/xsds/wsdlsoap.xsd