Metadata-Version: 1.0
Name: rsl.soap11
Version: 0.2.2
Summary: Remote Service Library soap 1.1 module
Home-page: http://rslib.sourceforge.net
Author: Gerhard Weis
Author-email: gerhard.weis@proclos.com
License: BSD
Platform: UNKNOWN
Classifier: Development Status :: 3 - Alpha
Classifier: Environment :: Web Environment
Classifier: Intended Audience :: Developers
Classifier: License :: OSI Approved :: BSD License
Classifier: Operating System :: OS Independent
Classifier: Programming Language :: Python
Classifier: Topic :: Internet
Classifier: Topic :: Software Development :: Libraries :: Python Modules
Classifier: Topic :: System :: Networking
